setup.py
ByteBeat/ByteBeat.py
ByteBeat/__init__.py
ByteBeat.egg-info/PKG-INFO
ByteBeat.egg-info/SOURCES.txt
ByteBeat.egg-info/dependency_links.txt
ByteBeat.egg-info/not-zip-safe
ByteBeat.egg-info/top_level.txt