Metadata-Version: 2.1
Name: ByteBeat
Version: 0.1
Summary: Run ByteBeat in Python 3!
Author: Itzsten
